insanely_fast_whisper-0.0.14.dist-info/METADATA
insanely_fast_whisper-0.0.14.dist-info/WHEEL
insanely_fast_whisper-0.0.14.dist-info/entry_points.txt
insanely_fast_whisper-0.0.14.dist-info/licenses/LICENSE
insanely_fast_whisper/__init__.py
insanely_fast_whisper/cli.py
insanely_fast_whisper/utils/__init__.py
insanely_fast_whisper/utils/diarization_pipeline.py
insanely_fast_whisper/utils/diarize.py
insanely_fast_whisper/utils/result.py
insanely_fast_whisper-0.0.14.dist-info/RECORD
