Metadata-Version: 2.1
Name: insanely-fast-whisper
Version: 0.0.14
Summary: An insanely fast whisper CLI
Author-Email: VB <reachvaibhavs10@gmail.com>, Patrick Arminio <patrick.arminio@gmail.com>
License: MIT
Project-URL: Homepage, https://github.com/Vaibhavs10/insanely-fast-whisper
Project-URL: Twitter, https://twitter.com/reach_vb
Requires-Python: >=3.8
Requires-Dist: transformers
Requires-Dist: optimum
Requires-Dist: accelerate
Requires-Dist: pyannote-audio>=3.1.0
Requires-Dist: setuptools>=68.2.2
Requires-Dist: rich>=13.7.0
